cegal/keystone_auth/__init__.py
cegal/keystone_auth/__main__.py
cegal/keystone_auth/authorize.py
cegal/keystone_auth/cache.py
cegal/keystone_auth/client.py
cegal/keystone_auth/contexts.py
cegal/keystone_auth/crypto.py
cegal/keystone_auth/db.py
cegal/keystone_auth/device.py
cegal/keystone_auth/exceptions.py
cegal/keystone_auth/identityserver.py
cegal/keystone_auth/listener.py
cegal/keystone_auth/nonce.py
cegal/keystone_auth/options.py
cegal/keystone_auth/pkce.py
cegal/keystone_auth/provider.py
cegal/keystone_auth/responses.py
cegal/keystone_auth/state.py
cegal/keystone_auth/storage.py
cegal/keystone_auth/tokens.py
cegal/keystone_auth/utils.py
cegal_keystoneauth-1.0.14.dist-info/licenses/LICENSE
cegal_keystoneauth-1.0.14.dist-info/METADATA
cegal_keystoneauth-1.0.14.dist-info/WHEEL
cegal_keystoneauth-1.0.14.dist-info/top_level.txt
cegal_keystoneauth-1.0.14.dist-info/RECORD
