Metadata-Version: 2.4
Name: cegal-keystoneauth
Version: 1.0.14
Summary: A Python package to handle Cegal Keystone tokens
Home-page: https://docs.prizm.cegal-geo.com/authentication/keystone.html
Author: Cegal Prizm Team
Author-email: prizm@cegal.com
Classifier: Programming Language :: Python :: 3
Classifier: License :: Other/Proprietary License
Classifier: Operating System :: OS Independent
Requires-Python: >=3.6
License-File: LICENSE
Requires-Dist: PyJWT>=2.2.0
Requires-Dist: requests>=2.26.0
Requires-Dist: cryptography>=35.0.0
Dynamic: author
Dynamic: author-email
Dynamic: classifier
Dynamic: description
Dynamic: description-content-type
Dynamic: home-page
Dynamic: license-file
Dynamic: requires-dist
Dynamic: requires-python
Dynamic: summary
